pyrpn/__init__.py
pyrpn/rpn.py
pyrpn-1.0.4.data/scripts/pyrpn
pyrpn-1.0.4.dist-info/DESCRIPTION.rst
pyrpn-1.0.4.dist-info/METADATA
pyrpn-1.0.4.dist-info/RECORD
pyrpn-1.0.4.dist-info/WHEEL
pyrpn-1.0.4.dist-info/metadata.json
pyrpn-1.0.4.dist-info/top_level.txt
