Metadata-Version: 2.0
Name: pyrpn
Version: 1.0.4
Summary: rpn calculator
Home-page: https://github.com/Archman/pyrpn
Author: Tong Zhang
Author-email: zhangtong@sinap.ac.cn
License: MIT
Platform: Linux
Classifier: Programming Language :: Python
